ai_network/__init__.py
ai_network/ai_network_types_pb2.py
ai_network/ai_network_types_pb2_grpc.py
ai_network/ai_network_utils_pb2.py
ai_network/ai_network_utils_pb2_grpc.py
ai_network/infer_pb2.py
ai_network/infer_pb2_grpc.py
ai_network/service_pb2.py
ai_network/service_pb2_grpc.py
ai_network/serving_pb2.py
ai_network/serving_pb2_grpc.py
zetta_grpc_protos-0.0.1.dist-info/METADATA
zetta_grpc_protos-0.0.1.dist-info/WHEEL
zetta_grpc_protos-0.0.1.dist-info/top_level.txt
zetta_grpc_protos-0.0.1.dist-info/RECORD
